manufacturing/__init__.py
manufacturing/alt_analysis.py
manufacturing/alt_vis.py
manufacturing/analysis.py
manufacturing/data_import.py
manufacturing/lookup_tables.py
manufacturing/report.py
manufacturing/util.py
manufacturing/visual.py
manufacturing-1.6.0.dist-info/METADATA
manufacturing-1.6.0.dist-info/WHEEL
manufacturing-1.6.0.dist-info/top_level.txt
manufacturing-1.6.0.dist-info/RECORD
