Metadata-Version: 2.1
Name: manufacturing
Version: 1.6.0
Summary: Six-Sigma based analysis of manufacturing data
Author-email: "Jason R. Jones" <slightlynybbled@gmail.com>
Project-URL: Documentation, https://slightlynybbled.github.io/manufacturing/index.html
Project-URL: Repository, https://github.com/slightlynybbled/manufacturing
Classifier: Development Status :: 4 - Beta
Classifier: Programming Language :: Python :: 3
Classifier: License :: OSI Approved :: MIT License
Classifier: Operating System :: OS Independent
Classifier: Intended Audience :: Manufacturing
Classifier: Natural Language :: English
Requires-Python: >=3.10
Requires-Dist: matplotlib>=3.8.0
Requires-Dist: openpyxl>=3.0.9
Requires-Dist: pandas>=2.2.0
Requires-Dist: scipy>=1.12.0
Requires-Dist: xlrd>=2.0.1
